simple_proxy/__init__.py
simple_proxy/proxy.py
CustomProxy-1.0.1.dist-info/LICENSE
CustomProxy-1.0.1.dist-info/METADATA
CustomProxy-1.0.1.dist-info/WHEEL
CustomProxy-1.0.1.dist-info/top_level.txt
CustomProxy-1.0.1.dist-info/RECORD
